chemap/__init__.py
chemap/approx_nn.py
chemap/data_loader.py
chemap/fingerprint_computation.py
chemap/fingerprint_conversions.py
chemap/fingerprint_statistics.py
chemap/mbp.py
chemap/metrics.py
chemap/utils.py
chemap/visualizations.py
chemap-0.2.0.dist-info/METADATA
chemap-0.2.0.dist-info/WHEEL
chemap-0.2.0.dist-info/licenses/LICENSE
chemap-0.2.0.dist-info/RECORD
