Metadata-Version: 2.4
Name: chemap
Version: 0.2.0
Summary: Library for computing molecular fingerprint based similarities as well as dimensionality reduction based chemical space visualizations. 
License-Expression: MIT
License-File: LICENSE
Author: Florian Huber
Author-email: florian.huber@hs-duesseldorf.de
Requires-Python: >=3.11,<3.14
Classifier: Programming Language :: Python :: 3
Classifier: Operating System :: OS Independent
Requires-Dist: joblib (>=1.3.2)
Requires-Dist: map4 (>=1.1.3)
Requires-Dist: matplotlib (>=3.10.1)
Requires-Dist: numba (>=0.61.2)
Requires-Dist: numpy (>=2.1.0)
Requires-Dist: pandas (>=2.2.1)
Requires-Dist: pooch (>=1.8.2)
Requires-Dist: rdkit (>=2024.9.6)
Requires-Dist: scikit-fingerprints (>=1.15.0)
Requires-Dist: scipy (>=1.14.2)
Requires-Dist: tqdm (>=4.67.1)
